[
  {
    "_id": {
      "$oid": "66716cb0e1a78e67dc8c8dbf"
    },
    "name": "Haldiram's",
    "isVeg": true,
    "address": "123 Main Street, City Center, Mumbai, India",
    "ratings": 3.5,
    "numOfReviews": 70,
    "location": {
      "type": "Point",
      "coordinates": [
        72.8777,
        19.076
      ]
    },
    "reviews": [
      {
        "name": "Aditya 1",
        "rating": 5,
        "Comment": "Veg Fried Rice was One of the best dishes I have tried."
      },
      {
        "name": "Rahul 2",
        "rating": 4,
        "Comment": "Dosa was Fresh and flavorful."
      },
      {
        "name": "Rahul 3",
        "rating": 5,
        "Comment": "Masala Dosa was Fresh and flavorful."
      },
      {
        "name": "Pooja 4",
        "rating": 3,
        "Comment": "Butter Naan was Portion size was acceptable."
      },
      {
        "name": "Rahul 5",
        "rating": 1,
        "Comment": "Butter Naan was Too much waiting time."
      },
      {
        "name": "Rohit 6",
        "rating": 4,
        "Comment": "Chicken Biryani was Fresh and flavorful."
      },
      {
        "name": "Karan 7",
        "rating": 2,
        "Comment": "Dosa was Service needs major improvement."
      },
      {
        "name": "Ananya 8",
        "rating": 4,
        "Comment": "Fried Chicken was Loved the quality and presentation."
      },
      {
        "name": "Pooja 9",
        "rating": 5,
        "Comment": "Pani Puri was Fresh and flavorful."
      },
      {
        "name": "Arjun 10",
        "rating": 5,
        "Comment": "Dosa was Loved the quality and presentation."
      },
      {
        "name": "Meera 11",
        "rating": 2,
        "Comment": "Chole Bhature was Food arrived cold."
      },
      {
        "name": "Kavya 12",
        "rating": 3,
        "Comment": "Chicken 65 was Average experience overall."
      },
      {
        "name": "Pooja 13",
        "rating": 4,
        "Comment": "Tandoori Chicken was Loved the quality and presentation."
      },
      {
        "name": "Pooja 14",
        "rating": 3,
        "Comment": "Butter Naan was Taste was okay, nothing extraordinary."
      },
      {
        "name": "Karan 15",
        "rating": 5,
        "Comment": "Momos was Loved the quality and presentation."
      },
      {
        "name": "Ananya 16",
        "rating": 4,
        "Comment": "Tandoori Chicken was Amazing taste, highly recommended."
      },
      {
        "name": "Karan 17",
        "rating": 4,
        "Comment": "Chicken 65 was One of the best dishes I have tried."
      },
      {
        "name": "Karan 18",
        "rating": 3,
        "Comment": "Paneer Butter Masala was Taste was okay, nothing extraordinary."
      },
      {
        "name": "Vikram 19",
        "rating": 1,
        "Comment": "Sushi was Not satisfied with the taste."
      },
      {
        "name": "Arjun 20",
        "rating": 4,
        "Comment": "Butter Naan was Loved the quality and presentation."
      },
      {
        "name": "Sneha 21",
        "rating": 3,
        "Comment": "Tandoori Chicken was Taste was okay, nothing extraordinary."
      },
      {
        "name": "Rahul 22",
        "rating": 3,
        "Comment": "Fried Chicken was Portion size was acceptable."
      },
      {
        "name": "Sanjay 23",
        "rating": 2,
        "Comment": "Mutton Biryani was Too much waiting time."
      },
      {
        "name": "Riya 24",
        "rating": 1,
        "Comment": "Chicken Biryani was Not satisfied with the taste."
      },
      {
        "name": "Riya 25",
        "rating": 5,
        "Comment": "Masala Dosa was Perfectly cooked and worth the price."
      },
      {
        "name": "Sneha 26",
        "rating": 5,
        "Comment": "Chole Bhature was Fresh and flavorful."
      },
      {
        "name": "Riya 27",
        "rating": 5,
        "Comment": "Dosa was Perfectly cooked and worth the price."
      },
      {
        "name": "Ananya 28",
        "rating": 2,
        "Comment": "Chicken Biryani was Service needs major improvement."
      },
      {
        "name": "Vikram 29",
        "rating": 2,
        "Comment": "Chicken 65 was Food arrived cold."
      },
      {
        "name": "Rohit 30",
        "rating": 4,
        "Comment": "Sushi was Loved the quality and presentation."
      },
      {
        "name": "Rahul 31",
        "rating": 3,
        "Comment": "Paneer Butter Masala was Food was decent but could be better."
      },
      {
        "name": "Manoj 32",
        "rating": 4,
        "Comment": "Masala Dosa was Loved the quality and presentation."
      },
      {
        "name": "Kavya 33",
        "rating": 3,
        "Comment": "Dosa was Taste was okay, nothing extraordinary."
      },
      {
        "name": "Divya 34",
        "rating": 1,
        "Comment": "Chole Bhature was Food arrived cold."
      },
      {
        "name": "Rahul 35",
        "rating": 5,
        "Comment": "Raj Kachori was Perfectly cooked and worth the price."
      },
      {
        "name": "Kavya 36",
        "rating": 3,
        "Comment": "Chole Bhature was Service and food were average."
      },
      {
        "name": "Priya 37",
        "rating": 2,
        "Comment": "Chicken Biryani was Not satisfied with the taste."
      },
      {
        "name": "Priya 38",
        "rating": 5,
        "Comment": "Chicken 65 was Fresh and flavorful."
      },
      {
        "name": "Arjun 39",
        "rating": 5,
        "Comment": "Tandoori Chicken was Perfectly cooked and worth the price."
      },
      {
        "name": "Aditya 40",
        "rating": 4,
        "Comment": "Fried Chicken was Fresh and flavorful."
      },
      {
        "name": "Vikram 41",
        "rating": 4,
        "Comment": "Veg Fried Rice was Loved the quality and presentation."
      },
      {
        "name": "Manoj 42",
        "rating": 3,
        "Comment": "Masala Dosa was Portion size was acceptable."
      },
      {
        "name": "Meera 43",
        "rating": 4,
        "Comment": "Sushi was Perfectly cooked and worth the price."
      },
      {
        "name": "Karan 44",
        "rating": 3,
        "Comment": "Sushi was Food was decent but could be better."
      },
      {
        "name": "Rohit 45",
        "rating": 5,
        "Comment": "Butter Naan was Amazing taste, highly recommended."
      },
      {
        "name": "Sanjay 46",
        "rating": 4,
        "Comment": "Chicken Biryani was Amazing taste, highly recommended."
      },
      {
        "name": "Rahul 47",
        "rating": 4,
        "Comment": "Pani Puri was Amazing taste, highly recommended."
      },
      {
        "name": "Divya 48",
        "rating": 3,
        "Comment": "Butter Naan was Average experience overall."
      },
      {
        "name": "Riya 49",
        "rating": 3,
        "Comment": "Veg Fried Rice was Service and food were average."
      },
      {
        "name": "Pooja 50",
        "rating": 5,
        "Comment": "Chicken Biryani was Fresh and flavorful."
      },
      {
        "name": "Aarav 51",
        "rating": 4,
        "Comment": "Chicken Biryani was Loved the quality and presentation."
      },
      {
        "name": "Rahul 52",
        "rating": 4,
        "Comment": "Fried Chicken was Perfectly cooked and worth the price."
      },
      {
        "name": "Vikram 53",
        "rating": 3,
        "Comment": "Veg Fried Rice was Average experience overall."
      },
      {
        "name": "Sanjay 54",
        "rating": 1,
        "Comment": "Paneer Butter Masala was Food arrived cold."
      },
      {
        "name": "Nitin 55",
        "rating": 3,
        "Comment": "Masala Dosa was Average experience overall."
      },
      {
        "name": "Ananya 56",
        "rating": 3,
        "Comment": "Chole Bhature was Taste was okay, nothing extraordinary."
      },
      {
        "name": "Rahul 57",
        "rating": 3,
        "Comment": "Mutton Biryani was Average experience overall."
      },
      {
        "name": "Neha 58",
        "rating": 3,
        "Comment": "Dosa was Food was decent but could be better."
      },
      {
        "name": "Aditya 59",
        "rating": 4,
        "Comment": "Masala Dosa was Loved the quality and presentation."
      },
      {
        "name": "Meera 60",
        "rating": 2,
        "Comment": "Momos was Service needs major improvement."
      },
      {
        "name": "Arjun 61",
        "rating": 5,
        "Comment": "Raj Kachori was Loved the quality and presentation."
      },
      {
        "name": "Vikram 62",
        "rating": 4,
        "Comment": "Masala Dosa was One of the best dishes I have tried."
      },
      {
        "name": "Ananya 63",
        "rating": 3,
        "Comment": "Pani Puri was Portion size was acceptable."
      },
      {
        "name": "Rahul 64",
        "rating": 4,
        "Comment": "Chicken Biryani was Perfectly cooked and worth the price."
      },
      {
        "name": "Aditya 65",
        "rating": 4,
        "Comment": "Butter Naan was Loved the quality and presentation."
      },
      {
        "name": "Rohit 66",
        "rating": 3,
        "Comment": "Raj Kachori was Average experience overall."
      },
      {
        "name": "Ishita 67",
        "rating": 4,
        "Comment": "Fried Chicken was Loved the quality and presentation."
      },
      {
        "name": "Aarav 68",
        "rating": 4,
        "Comment": "Pani Puri was Fresh and flavorful."
      },
      {
        "name": "Aditya 69",
        "rating": 4,
        "Comment": "Pani Puri was Loved the quality and presentation."
      },
      {
        "name": "Pooja 70",
        "rating": 4,
        "Comment": "Momos was Perfectly cooked and worth the price."
      }
    ],
    "images": [
      {
        "public_id": "haldirams_image_1",
        "url": "https://media-assets.swiggy.com/swiggy/image/upload/fl_lossy,f_auto,q_auto,w_366/1abb89624b491497c8cff182d95ac457"
      }
    ],
    "createdAt": "2024-06-13T12:00:00Z"
  },
  {
    "_id": {
      "$oid": "6671719fe1a78e67dc8c8dce"
    },
    "name": "Mani's Dum Biryani",
    "isVeg": false,
    "address": "Halasuru, Yellappa Chetty Layout, Sivanchetti Gardens, Bengaluru, Karnataka 560042",
    "ratings": 3.5,
    "numOfReviews": 70,
    "location": {
      "type": "Point",
      "coordinates": [
        77.5946,
        12.9716
      ]
    },
    "reviews": [
      {
        "name": "Ishita 1",
        "rating": 5,
        "Comment": "Chicken Biryani was Fresh and flavorful."
      },
      {
        "name": "Meera 2",
        "rating": 5,
        "Comment": "Chicken 65 was Loved the quality and presentation."
      },
      {
        "name": "Rahul 3",
        "rating": 4,
        "Comment": "Sushi was Loved the quality and presentation."
      },
      {
        "name": "Sneha 4",
        "rating": 5,
        "Comment": "Butter Naan was Perfectly cooked and worth the price."
      },
      {
        "name": "Meera 5",
        "rating": 4,
        "Comment": "Chicken Biryani was One of the best dishes I have tried."
      },
      {
        "name": "Arjun 6",
        "rating": 4,
        "Comment": "Pani Puri was Loved the quality and presentation."
      },
      {
        "name": "Rahul 7",
        "rating": 5,
        "Comment": "Pani Puri was Fresh and flavorful."
      },
      {
        "name": "Arjun 8",
        "rating": 3,
        "Comment": "Paneer Butter Masala was Food was decent but could be better."
      },
      {
        "name": "Meera 9",
        "rating": 3,
        "Comment": "Tandoori Chicken was Taste was okay, nothing extraordinary."
      },
      {
        "name": "Rahul 10",
        "rating": 5,
        "Comment": "Chole Bhature was One of the best dishes I have tried."
      },
      {
        "name": "Neha 11",
        "rating": 5,
        "Comment": "Paneer Butter Masala was Fresh and flavorful."
      },
      {
        "name": "Riya 12",
        "rating": 2,
        "Comment": "Dosa was Food arrived cold."
      },
      {
        "name": "Neha 13",
        "rating": 5,
        "Comment": "Raj Kachori was One of the best dishes I have tried."
      },
      {
        "name": "Priya 14",
        "rating": 1,
        "Comment": "Dosa was Not satisfied with the taste."
      },
      {
        "name": "Riya 15",
        "rating": 3,
        "Comment": "Butter Naan was Average experience overall."
      },
      {
        "name": "Aarav 16",
        "rating": 5,
        "Comment": "Tandoori Chicken was One of the best dishes I have tried."
      },
      {
        "name": "Rahul 17",
        "rating": 4,
        "Comment": "Paneer Butter Masala was Loved the quality and presentation."
      },
      {
        "name": "Aarav 18",
        "rating": 3,
        "Comment": "Fried Chicken was Average experience overall."
      },
      {
        "name": "Arjun 19",
        "rating": 3,
        "Comment": "Mutton Biryani was Portion size was acceptable."
      },
      {
        "name": "Rahul 20",
        "rating": 5,
        "Comment": "Paneer Butter Masala was One of the best dishes I have tried."
      },
      {
        "name": "Rohit 21",
        "rating": 3,
        "Comment": "Pani Puri was Food was decent but could be better."
      },
      {
        "name": "Manoj 22",
        "rating": 2,
        "Comment": "Mutton Biryani was Food arrived cold."
      },
      {
        "name": "Priya 23",
        "rating": 4,
        "Comment": "Chicken Biryani was One of the best dishes I have tried."
      },
      {
        "name": "Riya 24",
        "rating": 2,
        "Comment": "Masala Dosa was Service needs major improvement."
      },
      {
        "name": "Riya 25",
        "rating": 4,
        "Comment": "Dosa was Perfectly cooked and worth the price."
      },
      {
        "name": "Aarav 26",
        "rating": 5,
        "Comment": "Veg Fried Rice was Amazing taste, highly recommended."
      },
      {
        "name": "Priya 27",
        "rating": 1,
        "Comment": "Momos was Food arrived cold."
      },
      {
        "name": "Vikram 28",
        "rating": 2,
        "Comment": "Chole Bhature was Overpriced for the quality offered."
      },
      {
        "name": "Pooja 29",
        "rating": 5,
        "Comment": "Raj Kachori was One of the best dishes I have tried."
      },
      {
        "name": "Pooja 30",
        "rating": 5,
        "Comment": "Chicken Biryani was Fresh and flavorful."
      },
      {
        "name": "Rahul 31",
        "rating": 3,
        "Comment": "Chicken Biryani was Average experience overall."
      },
      {
        "name": "Divya 32",
        "rating": 2,
        "Comment": "Paneer Butter Masala was Service needs major improvement."
      },
      {
        "name": "Priya 33",
        "rating": 2,
        "Comment": "Momos was Service needs major improvement."
      },
      {
        "name": "Karan 34",
        "rating": 5,
        "Comment": "Momos was Amazing taste, highly recommended."
      },
      {
        "name": "Karan 35",
        "rating": 3,
        "Comment": "Pani Puri was Food was decent but could be better."
      },
      {
        "name": "Riya 36",
        "rating": 3,
        "Comment": "Masala Dosa was Service and food were average."
      },
      {
        "name": "Rohit 37",
        "rating": 2,
        "Comment": "Pani Puri was Service needs major improvement."
      },
      {
        "name": "Arjun 38",
        "rating": 3,
        "Comment": "Raj Kachori was Taste was okay, nothing extraordinary."
      },
      {
        "name": "Meera 39",
        "rating": 5,
        "Comment": "Chicken 65 was Fresh and flavorful."
      },
      {
        "name": "Vikram 40",
        "rating": 3,
        "Comment": "Paneer Butter Masala was Average experience overall."
      },
      {
        "name": "Priya 41",
        "rating": 3,
        "Comment": "Fried Chicken was Service and food were average."
      },
      {
        "name": "Riya 42",
        "rating": 2,
        "Comment": "Butter Naan was Service needs major improvement."
      },
      {
        "name": "Rahul 43",
        "rating": 1,
        "Comment": "Fried Chicken was Not satisfied with the taste."
      },
      {
        "name": "Aarav 44",
        "rating": 5,
        "Comment": "Mutton Biryani was One of the best dishes I have tried."
      },
      {
        "name": "Riya 45",
        "rating": 2,
        "Comment": "Pani Puri was Not satisfied with the taste."
      },
      {
        "name": "Ananya 46",
        "rating": 2,
        "Comment": "Veg Fried Rice was Service needs major improvement."
      },
      {
        "name": "Priya 47",
        "rating": 1,
        "Comment": "Chole Bhature was Not satisfied with the taste."
      },
      {
        "name": "Aarav 48",
        "rating": 1,
        "Comment": "Tandoori Chicken was Overpriced for the quality offered."
      },
      {
        "name": "Meera 49",
        "rating": 3,
        "Comment": "Tandoori Chicken was Food was decent but could be better."
      },
      {
        "name": "Priya 50",
        "rating": 1,
        "Comment": "Tandoori Chicken was Food arrived cold."
      },
      {
        "name": "Sanjay 51",
        "rating": 2,
        "Comment": "Pani Puri was Overpriced for the quality offered."
      },
      {
        "name": "Priya 52",
        "rating": 3,
        "Comment": "Mutton Biryani was Food was decent but could be better."
      },
      {
        "name": "Nitin 53",
        "rating": 3,
        "Comment": "Masala Dosa was Taste was okay, nothing extraordinary."
      },
      {
        "name": "Neha 54",
        "rating": 4,
        "Comment": "Sushi was One of the best dishes I have tried."
      },
      {
        "name": "Sneha 55",
        "rating": 5,
        "Comment": "Sushi was Fresh and flavorful."
      },
      {
        "name": "Neha 56",
        "rating": 5,
        "Comment": "Chole Bhature was Fresh and flavorful."
      },
      {
        "name": "Aarav 57",
        "rating": 3,
        "Comment": "Raj Kachori was Portion size was acceptable."
      },
      {
        "name": "Karan 58",
        "rating": 5,
        "Comment": "Chole Bhature was One of the best dishes I have tried."
      },
      {
        "name": "Riya 59",
        "rating": 5,
        "Comment": "Raj Kachori was Amazing taste, highly recommended."
      },
      {
        "name": "Ananya 60",
        "rating": 4,
        "Comment": "Fried Chicken was Fresh and flavorful."
      },
      {
        "name": "Priya 61",
        "rating": 3,
        "Comment": "Tandoori Chicken was Portion size was acceptable."
      },
      {
        "name": "Manoj 62",
        "rating": 4,
        "Comment": "Butter Naan was Loved the quality and presentation."
      },
      {
        "name": "Rohit 63",
        "rating": 4,
        "Comment": "Veg Fried Rice was One of the best dishes I have tried."
      },
      {
        "name": "Rohit 64",
        "rating": 5,
        "Comment": "Mutton Biryani was Perfectly cooked and worth the price."
      },
      {
        "name": "Rahul 65",
        "rating": 5,
        "Comment": "Masala Dosa was One of the best dishes I have tried."
      },
      {
        "name": "Ishita 66",
        "rating": 4,
        "Comment": "Chicken 65 was Loved the quality and presentation."
      },
      {
        "name": "Neha 67",
        "rating": 1,
        "Comment": "Chicken Biryani was Overpriced for the quality offered."
      },
      {
        "name": "Ananya 68",
        "rating": 4,
        "Comment": "Mutton Biryani was Fresh and flavorful."
      },
      {
        "name": "Nitin 69",
        "rating": 4,
        "Comment": "Masala Dosa was Loved the quality and presentation."
      },
      {
        "name": "Meera 70",
        "rating": 5,
        "Comment": "Chicken 65 was Amazing taste, highly recommended."
      }
    ],
    "images": [
      {
        "public_id": "image1",
        "url": "https://media-assets.swiggy.com/swiggy/image/upload/fl_lossy,f_auto,q_auto,w_264,h_288,c_fill/e6bfe20a8b03779efebeb04eae9a86c6"
      }
    ],
    "createdAt": "2023-06-17T12:00:00Z"
  },
  {
    "_id": {
      "$oid": "667167a4a0215dd827e9d81e"
    },
    "name": "Dindigul Thalappakatti",
    "isVeg": false,
    "address": "1st floor, Ramanashree Arcade, Old Kids Kemp, Mahatma Gandhi Rd, Craig Park Layout, Ashok Nagar, Bengaluru, Karnataka 560001",
    "ratings": 3.3,
    "numOfReviews": 70,
    "location": {
      "type": "Point",
      "coordinates": [
        12.9812533,
        77.5670007
      ]
    },
    "reviews": [
      {
        "name": "Neha 1",
        "rating": 2,
        "Comment": "Fried Chicken was Overpriced for the quality offered."
      },
      {
        "name": "Sneha 2",
        "rating": 1,
        "Comment": "Chicken 65 was Not satisfied with the taste."
      },
      {
        "name": "Neha 3",
        "rating": 4,
        "Comment": "Chole Bhature was One of the best dishes I have tried."
      },
      {
        "name": "Neha 4",
        "rating": 1,
        "Comment": "Pani Puri was Service needs major improvement."
      },
      {
        "name": "Meera 5",
        "rating": 5,
        "Comment": "Sushi was Fresh and flavorful."
      },
      {
        "name": "Arjun 6",
        "rating": 3,
        "Comment": "Raj Kachori was Food was decent but could be better."
      },
      {
        "name": "Karan 7",
        "rating": 5,
        "Comment": "Dosa was Fresh and flavorful."
      },
      {
        "name": "Nitin 8",
        "rating": 3,
        "Comment": "Raj Kachori was Average experience overall."
      },
      {
        "name": "Manoj 9",
        "rating": 4,
        "Comment": "Dosa was One of the best dishes I have tried."
      },
      {
        "name": "Sanjay 10",
        "rating": 4,
        "Comment": "Chole Bhature was Amazing taste, highly recommended."
      },
      {
        "name": "Karan 11",
        "rating": 3,
        "Comment": "Dosa was Food was decent but could be better."
      },
      {
        "name": "Divya 12",
        "rating": 3,
        "Comment": "Momos was Portion size was acceptable."
      },
      {
        "name": "Rohit 13",
        "rating": 4,
        "Comment": "Veg Fried Rice was Fresh and flavorful."
      },
      {
        "name": "Kavya 14",
        "rating": 2,
        "Comment": "Fried Chicken was Food arrived cold."
      },
      {
        "name": "Riya 15",
        "rating": 2,
        "Comment": "Masala Dosa was Overpriced for the quality offered."
      },
      {
        "name": "Sanjay 16",
        "rating": 2,
        "Comment": "Chole Bhature was Too much waiting time."
      },
      {
        "name": "Arjun 17",
        "rating": 5,
        "Comment": "Mutton Biryani was Fresh and flavorful."
      },
      {
        "name": "Priya 18",
        "rating": 3,
        "Comment": "Paneer Butter Masala was Service and food were average."
      },
      {
        "name": "Sanjay 19",
        "rating": 2,
        "Comment": "Chicken Biryani was Service needs major improvement."
      },
      {
        "name": "Nitin 20",
        "rating": 2,
        "Comment": "Veg Fried Rice was Service needs major improvement."
      },
      {
        "name": "Riya 21",
        "rating": 4,
        "Comment": "Chicken 65 was Loved the quality and presentation."
      },
      {
        "name": "Rohit 22",
        "rating": 2,
        "Comment": "Paneer Butter Masala was Too much waiting time."
      },
      {
        "name": "Sanjay 23",
        "rating": 3,
        "Comment": "Tandoori Chicken was Average experience overall."
      },
      {
        "name": "Vikram 24",
        "rating": 5,
        "Comment": "Chicken Biryani was Amazing taste, highly recommended."
      },
      {
        "name": "Sneha 25",
        "rating": 2,
        "Comment": "Paneer Butter Masala was Service needs major improvement."
      },
      {
        "name": "Divya 26",
        "rating": 4,
        "Comment": "Masala Dosa was Amazing taste, highly recommended."
      },
      {
        "name": "Manoj 27",
        "rating": 5,
        "Comment": "Paneer Butter Masala was Amazing taste, highly recommended."
      },
      {
        "name": "Rohit 28",
        "rating": 5,
        "Comment": "Dosa was Loved the quality and presentation."
      },
      {
        "name": "Meera 29",
        "rating": 2,
        "Comment": "Chole Bhature was Service needs major improvement."
      },
      {
        "name": "Kavya 30",
        "rating": 3,
        "Comment": "Butter Naan was Taste was okay, nothing extraordinary."
      },
      {
        "name": "Divya 31",
        "rating": 5,
        "Comment": "Tandoori Chicken was One of the best dishes I have tried."
      },
      {
        "name": "Neha 32",
        "rating": 3,
        "Comment": "Paneer Butter Masala was Taste was okay, nothing extraordinary."
      },
      {
        "name": "Rahul 33",
        "rating": 5,
        "Comment": "Chole Bhature was One of the best dishes I have tried."
      },
      {
        "name": "Ananya 34",
        "rating": 5,
        "Comment": "Dosa was One of the best dishes I have tried."
      },
      {
        "name": "Aarav 35",
        "rating": 3,
        "Comment": "Fried Chicken was Portion size was acceptable."
      },
      {
        "name": "Aarav 36",
        "rating": 5,
        "Comment": "Sushi was Perfectly cooked and worth the price."
      },
      {
        "name": "Neha 37",
        "rating": 5,
        "Comment": "Chole Bhature was Perfectly cooked and worth the price."
      },
      {
        "name": "Sanjay 38",
        "rating": 3,
        "Comment": "Mutton Biryani was Portion size was acceptable."
      },
      {
        "name": "Arjun 39",
        "rating": 2,
        "Comment": "Butter Naan was Too much waiting time."
      },
      {
        "name": "Riya 40",
        "rating": 1,
        "Comment": "Dosa was Service needs major improvement."
      },
      {
        "name": "Karan 41",
        "rating": 2,
        "Comment": "Pani Puri was Too much waiting time."
      },
      {
        "name": "Nitin 42",
        "rating": 1,
        "Comment": "Paneer Butter Masala was Not satisfied with the taste."
      },
      {
        "name": "Ananya 43",
        "rating": 1,
        "Comment": "Masala Dosa was Food arrived cold."
      },
      {
        "name": "Vikram 44",
        "rating": 1,
        "Comment": "Dosa was Not satisfied with the taste."
      },
      {
        "name": "Manoj 45",
        "rating": 2,
        "Comment": "Chole Bhature was Food arrived cold."
      },
      {
        "name": "Aarav 46",
        "rating": 1,
        "Comment": "Chicken Biryani was Overpriced for the quality offered."
      },
      {
        "name": "Ananya 47",
        "rating": 4,
        "Comment": "Raj Kachori was Perfectly cooked and worth the price."
      },
      {
        "name": "Riya 48",
        "rating": 1,
        "Comment": "Chicken Biryani was Overpriced for the quality offered."
      },
      {
        "name": "Priya 49",
        "rating": 5,
        "Comment": "Chicken Biryani was One of the best dishes I have tried."
      },
      {
        "name": "Aditya 50",
        "rating": 3,
        "Comment": "Pani Puri was Taste was okay, nothing extraordinary."
      },
      {
        "name": "Vikram 51",
        "rating": 3,
        "Comment": "Pani Puri was Portion size was acceptable."
      },
      {
        "name": "Karan 52",
        "rating": 3,
        "Comment": "Paneer Butter Masala was Service and food were average."
      },
      {
        "name": "Riya 53",
        "rating": 2,
        "Comment": "Veg Fried Rice was Food arrived cold."
      },
      {
        "name": "Neha 54",
        "rating": 4,
        "Comment": "Chicken Biryani was Perfectly cooked and worth the price."
      },
      {
        "name": "Rohit 55",
        "rating": 3,
        "Comment": "Chicken 65 was Food was decent but could be better."
      },
      {
        "name": "Karan 56",
        "rating": 4,
        "Comment": "Masala Dosa was Perfectly cooked and worth the price."
      },
      {
        "name": "Riya 57",
        "rating": 3,
        "Comment": "Butter Naan was Taste was okay, nothing extraordinary."
      },
      {
        "name": "Sanjay 58",
        "rating": 5,
        "Comment": "Masala Dosa was Amazing taste, highly recommended."
      },
      {
        "name": "Meera 59",
        "rating": 5,
        "Comment": "Chicken 65 was Perfectly cooked and worth the price."
      },
      {
        "name": "Rahul 60",
        "rating": 5,
        "Comment": "Raj Kachori was Amazing taste, highly recommended."
      },
      {
        "name": "Arjun 61",
        "rating": 5,
        "Comment": "Butter Naan was Perfectly cooked and worth the price."
      },
      {
        "name": "Meera 62",
        "rating": 3,
        "Comment": "Masala Dosa was Food was decent but could be better."
      },
      {
        "name": "Vikram 63",
        "rating": 5,
        "Comment": "Chicken Biryani was Loved the quality and presentation."
      },
      {
        "name": "Manoj 64",
        "rating": 2,
        "Comment": "Chicken Biryani was Overpriced for the quality offered."
      },
      {
        "name": "Sanjay 65",
        "rating": 1,
        "Comment": "Fried Chicken was Too much waiting time."
      },
      {
        "name": "Karan 66",
        "rating": 5,
        "Comment": "Veg Fried Rice was Fresh and flavorful."
      },
      {
        "name": "Arjun 67",
        "rating": 5,
        "Comment": "Butter Naan was Perfectly cooked and worth the price."
      },
      {
        "name": "Nitin 68",
        "rating": 2,
        "Comment": "Tandoori Chicken was Too much waiting time."
      },
      {
        "name": "Sanjay 69",
        "rating": 5,
        "Comment": "Sushi was One of the best dishes I have tried."
      },
      {
        "name": "Meera 70",
        "rating": 5,
        "Comment": "Pani Puri was One of the best dishes I have tried."
      }
    ],
    "images": [
      {
        "public_id": "restaurant1_image1",
        "url": "https://upload.wikimedia.org/wikipedia/en/e/e6/Logo_of_Dindigul_Thalappakatti_Restaurant.png"
      }
    ],
    "createdAt": "2023-01-01T00:00:00Z"
  },
  {
    "_id": {
      "$oid": "667164e6bd4249c429fee778"
    },
    "name": "KFC",
    "isVeg": false,
    "address": "456 Fried Chicken Avenue, Koramangala, Bengaluru 560001",
    "ratings": 3.2,
    "numOfReviews": 70,
    "location": {
      "type": "Point",
      "coordinates": [
        12.935832,
        77.615038
      ]
    },
    "reviews": [
      {
        "name": "Sanjay 1",
        "rating": 4,
        "Comment": "Paneer Butter Masala was Fresh and flavorful."
      },
      {
        "name": "Arjun 2",
        "rating": 4,
        "Comment": "Fried Chicken was Loved the quality and presentation."
      },
      {
        "name": "Rahul 3",
        "rating": 5,
        "Comment": "Chicken 65 was Loved the quality and presentation."
      },
      {
        "name": "Arjun 4",
        "rating": 4,
        "Comment": "Sushi was One of the best dishes I have tried."
      },
      {
        "name": "Kavya 5",
        "rating": 2,
        "Comment": "Tandoori Chicken was Food arrived cold."
      },
      {
        "name": "Divya 6",
        "rating": 4,
        "Comment": "Butter Naan was One of the best dishes I have tried."
      },
      {
        "name": "Arjun 7",
        "rating": 1,
        "Comment": "Momos was Not satisfied with the taste."
      },
      {
        "name": "Sneha 8",
        "rating": 3,
        "Comment": "Sushi was Taste was okay, nothing extraordinary."
      },
      {
        "name": "Aarav 9",
        "rating": 3,
        "Comment": "Masala Dosa was Taste was okay, nothing extraordinary."
      },
      {
        "name": "Neha 10",
        "rating": 4,
        "Comment": "Mutton Biryani was Amazing taste, highly recommended."
      },
      {
        "name": "Rahul 11",
        "rating": 5,
        "Comment": "Raj Kachori was One of the best dishes I have tried."
      },
      {
        "name": "Vikram 12",
        "rating": 4,
        "Comment": "Paneer Butter Masala was Amazing taste, highly recommended."
      },
      {
        "name": "Meera 13",
        "rating": 3,
        "Comment": "Raj Kachori was Service and food were average."
      },
      {
        "name": "Kavya 14",
        "rating": 3,
        "Comment": "Dosa was Average experience overall."
      },
      {
        "name": "Riya 15",
        "rating": 5,
        "Comment": "Butter Naan was Perfectly cooked and worth the price."
      },
      {
        "name": "Rohit 16",
        "rating": 4,
        "Comment": "Veg Fried Rice was Perfectly cooked and worth the price."
      },
      {
        "name": "Rohit 17",
        "rating": 3,
        "Comment": "Chole Bhature was Food was decent but could be better."
      },
      {
        "name": "Aditya 18",
        "rating": 2,
        "Comment": "Dosa was Overpriced for the quality offered."
      },
      {
        "name": "Karan 19",
        "rating": 3,
        "Comment": "Raj Kachori was Average experience overall."
      },
      {
        "name": "Ishita 20",
        "rating": 5,
        "Comment": "Raj Kachori was Amazing taste, highly recommended."
      },
      {
        "name": "Sneha 21",
        "rating": 2,
        "Comment": "Paneer Butter Masala was Food arrived cold."
      },
      {
        "name": "Ishita 22",
        "rating": 1,
        "Comment": "Raj Kachori was Overpriced for the quality offered."
      },
      {
        "name": "Ishita 23",
        "rating": 2,
        "Comment": "Masala Dosa was Not satisfied with the taste."
      },
      {
        "name": "Manoj 24",
        "rating": 2,
        "Comment": "Mutton Biryani was Food arrived cold."
      },
      {
        "name": "Karan 25",
        "rating": 2,
        "Comment": "Chole Bhature was Overpriced for the quality offered."
      },
      {
        "name": "Kavya 26",
        "rating": 3,
        "Comment": "Chicken 65 was Average experience overall."
      },
      {
        "name": "Sanjay 27",
        "rating": 2,
        "Comment": "Chole Bhature was Overpriced for the quality offered."
      },
      {
        "name": "Meera 28",
        "rating": 1,
        "Comment": "Paneer Butter Masala was Food arrived cold."
      },
      {
        "name": "Rohit 29",
        "rating": 5,
        "Comment": "Paneer Butter Masala was Amazing taste, highly recommended."
      },
      {
        "name": "Karan 30",
        "rating": 2,
        "Comment": "Momos was Not satisfied with the taste."
      },
      {
        "name": "Rohit 31",
        "rating": 3,
        "Comment": "Chicken Biryani was Taste was okay, nothing extraordinary."
      },
      {
        "name": "Karan 32",
        "rating": 4,
        "Comment": "Butter Naan was Fresh and flavorful."
      },
      {
        "name": "Riya 33",
        "rating": 4,
        "Comment": "Raj Kachori was Fresh and flavorful."
      },
      {
        "name": "Rahul 34",
        "rating": 2,
        "Comment": "Tandoori Chicken was Overpriced for the quality offered."
      },
      {
        "name": "Aarav 35",
        "rating": 2,
        "Comment": "Mutton Biryani was Overpriced for the quality offered."
      },
      {
        "name": "Aditya 36",
        "rating": 1,
        "Comment": "Butter Naan was Service needs major improvement."
      },
      {
        "name": "Neha 37",
        "rating": 3,
        "Comment": "Momos was Taste was okay, nothing extraordinary."
      },
      {
        "name": "Rahul 38",
        "rating": 4,
        "Comment": "Momos was Loved the quality and presentation."
      },
      {
        "name": "Priya 39",
        "rating": 5,
        "Comment": "Momos was One of the best dishes I have tried."
      },
      {
        "name": "Arjun 40",
        "rating": 3,
        "Comment": "Mutton Biryani was Service and food were average."
      },
      {
        "name": "Aditya 41",
        "rating": 5,
        "Comment": "Masala Dosa was One of the best dishes I have tried."
      },
      {
        "name": "Rahul 42",
        "rating": 4,
        "Comment": "Chicken Biryani was Perfectly cooked and worth the price."
      },
      {
        "name": "Meera 43",
        "rating": 2,
        "Comment": "Tandoori Chicken was Service needs major improvement."
      },
      {
        "name": "Meera 44",
        "rating": 1,
        "Comment": "Raj Kachori was Overpriced for the quality offered."
      },
      {
        "name": "Nitin 45",
        "rating": 5,
        "Comment": "Pani Puri was Loved the quality and presentation."
      },
      {
        "name": "Ananya 46",
        "rating": 4,
        "Comment": "Chole Bhature was Loved the quality and presentation."
      },
      {
        "name": "Aditya 47",
        "rating": 2,
        "Comment": "Chicken Biryani was Service needs major improvement."
      },
      {
        "name": "Kavya 48",
        "rating": 3,
        "Comment": "Pani Puri was Service and food were average."
      },
      {
        "name": "Priya 49",
        "rating": 4,
        "Comment": "Sushi was Loved the quality and presentation."
      },
      {
        "name": "Arjun 50",
        "rating": 2,
        "Comment": "Mutton Biryani was Service needs major improvement."
      },
      {
        "name": "Ananya 51",
        "rating": 2,
        "Comment": "Chole Bhature was Not satisfied with the taste."
      },
      {
        "name": "Neha 52",
        "rating": 1,
        "Comment": "Sushi was Too much waiting time."
      },
      {
        "name": "Nitin 53",
        "rating": 4,
        "Comment": "Fried Chicken was Loved the quality and presentation."
      },
      {
        "name": "Divya 54",
        "rating": 2,
        "Comment": "Dosa was Not satisfied with the taste."
      },
      {
        "name": "Pooja 55",
        "rating": 3,
        "Comment": "Pani Puri was Portion size was acceptable."
      },
      {
        "name": "Priya 56",
        "rating": 2,
        "Comment": "Chole Bhature was Too much waiting time."
      },
      {
        "name": "Meera 57",
        "rating": 5,
        "Comment": "Pani Puri was Amazing taste, highly recommended."
      },
      {
        "name": "Neha 58",
        "rating": 1,
        "Comment": "Chole Bhature was Not satisfied with the taste."
      },
      {
        "name": "Riya 59",
        "rating": 5,
        "Comment": "Masala Dosa was Perfectly cooked and worth the price."
      },
      {
        "name": "Aarav 60",
        "rating": 5,
        "Comment": "Sushi was Fresh and flavorful."
      },
      {
        "name": "Pooja 61",
        "rating": 5,
        "Comment": "Sushi was Perfectly cooked and worth the price."
      },
      {
        "name": "Ishita 62",
        "rating": 5,
        "Comment": "Chole Bhature was Amazing taste, highly recommended."
      },
      {
        "name": "Neha 63",
        "rating": 4,
        "Comment": "Paneer Butter Masala was Loved the quality and presentation."
      },
      {
        "name": "Nitin 64",
        "rating": 4,
        "Comment": "Paneer Butter Masala was Fresh and flavorful."
      },
      {
        "name": "Sneha 65",
        "rating": 5,
        "Comment": "Chicken 65 was One of the best dishes I have tried."
      },
      {
        "name": "Sneha 66",
        "rating": 1,
        "Comment": "Sushi was Food arrived cold."
      },
      {
        "name": "Karan 67",
        "rating": 5,
        "Comment": "Sushi was One of the best dishes I have tried."
      },
      {
        "name": "Rohit 68",
        "rating": 5,
        "Comment": "Chole Bhature was Fresh and flavorful."
      },
      {
        "name": "Riya 69",
        "rating": 3,
        "Comment": "Chicken 65 was Portion size was acceptable."
      },
      {
        "name": "Rahul 70",
        "rating": 4,
        "Comment": "Dosa was Fresh and flavorful."
      }
    ],
    "images": [
      {
        "public_id": "kfc_001",
        "url": "https://shorturl.at/LpS17"
      },
      {
        "public_id": "kfc_002",
        "url": "https://shorturl.at/mNkWv"
      },
      {
        "public_id": "kfc_003",
        "url": "https://shorturl.at/3i04d"
      },
      {
        "public_id": "kfc_004",
        "url": "https://shorturl.at/6aIhg"
      }
    ],
    "createdAt": "2024-06-18T00:00:00Z"
  },
  {
    "_id": {
      "$oid": "66716f8c945c5a8b80d4631e"
    },
    "name": "Empire restaurant ",
    "isVeg": false,
    "address": "36, Church Street, Off, Mahatma Gandhi Rd, Bengaluru, Karnataka 560001",
    "ratings": 3.6,
    "numOfReviews": 70,
    "location": {
      "type": "Point",
      "coordinates": [
        12.9753943,
        77.5847828
      ]
    },
    "reviews": [
      {
        "name": "Manoj 1",
        "rating": 2,
        "Comment": "Butter Naan was Overpriced for the quality offered."
      },
      {
        "name": "Aarav 2",
        "rating": 4,
        "Comment": "Paneer Butter Masala was One of the best dishes I have tried."
      },
      {
        "name": "Pooja 3",
        "rating": 4,
        "Comment": "Chole Bhature was One of the best dishes I have tried."
      },
      {
        "name": "Sneha 4",
        "rating": 5,
        "Comment": "Tandoori Chicken was Perfectly cooked and worth the price."
      },
      {
        "name": "Sanjay 5",
        "rating": 3,
        "Comment": "Momos was Taste was okay, nothing extraordinary."
      },
      {
        "name": "Kavya 6",
        "rating": 3,
        "Comment": "Veg Fried Rice was Taste was okay, nothing extraordinary."
      },
      {
        "name": "Aarav 7",
        "rating": 2,
        "Comment": "Mutton Biryani was Overpriced for the quality offered."
      },
      {
        "name": "Ishita 8",
        "rating": 5,
        "Comment": "Chicken 65 was Fresh and flavorful."
      },
      {
        "name": "Vikram 9",
        "rating": 5,
        "Comment": "Sushi was Fresh and flavorful."
      },
      {
        "name": "Vikram 10",
        "rating": 3,
        "Comment": "Raj Kachori was Taste was okay, nothing extraordinary."
      },
      {
        "name": "Manoj 11",
        "rating": 5,
        "Comment": "Dosa was Loved the quality and presentation."
      },
      {
        "name": "Pooja 12",
        "rating": 5,
        "Comment": "Tandoori Chicken was One of the best dishes I have tried."
      },
      {
        "name": "Karan 13",
        "rating": 4,
        "Comment": "Raj Kachori was Fresh and flavorful."
      },
      {
        "name": "Meera 14",
        "rating": 2,
        "Comment": "Chicken Biryani was Service needs major improvement."
      },
      {
        "name": "Priya 15",
        "rating": 1,
        "Comment": "Paneer Butter Masala was Not satisfied with the taste."
      },
      {
        "name": "Aditya 16",
        "rating": 2,
        "Comment": "Pani Puri was Overpriced for the quality offered."
      },
      {
        "name": "Vikram 17",
        "rating": 2,
        "Comment": "Paneer Butter Masala was Service needs major improvement."
      },
      {
        "name": "Pooja 18",
        "rating": 2,
        "Comment": "Raj Kachori was Service needs major improvement."
      },
      {
        "name": "Sanjay 19",
        "rating": 5,
        "Comment": "Chicken Biryani was Perfectly cooked and worth the price."
      },
      {
        "name": "Neha 20",
        "rating": 1,
        "Comment": "Chicken Biryani was Not satisfied with the taste."
      },
      {
        "name": "Ishita 21",
        "rating": 5,
        "Comment": "Chicken 65 was Perfectly cooked and worth the price."
      },
      {
        "name": "Sneha 22",
        "rating": 3,
        "Comment": "Dosa was Average experience overall."
      },
      {
        "name": "Meera 23",
        "rating": 4,
        "Comment": "Butter Naan was Perfectly cooked and worth the price."
      },
      {
        "name": "Aarav 24",
        "rating": 2,
        "Comment": "Chole Bhature was Service needs major improvement."
      },
      {
        "name": "Nitin 25",
        "rating": 4,
        "Comment": "Sushi was One of the best dishes I have tried."
      },
      {
        "name": "Meera 26",
        "rating": 4,
        "Comment": "Pani Puri was Fresh and flavorful."
      },
      {
        "name": "Arjun 27",
        "rating": 3,
        "Comment": "Mutton Biryani was Portion size was acceptable."
      },
      {
        "name": "Pooja 28",
        "rating": 3,
        "Comment": "Tandoori Chicken was Service and food were average."
      },
      {
        "name": "Priya 29",
        "rating": 4,
        "Comment": "Pani Puri was Loved the quality and presentation."
      },
      {
        "name": "Pooja 30",
        "rating": 1,
        "Comment": "Chole Bhature was Overpriced for the quality offered."
      },
      {
        "name": "Divya 31",
        "rating": 5,
        "Comment": "Paneer Butter Masala was Fresh and flavorful."
      },
      {
        "name": "Pooja 32",
        "rating": 5,
        "Comment": "Raj Kachori was Loved the quality and presentation."
      },
      {
        "name": "Ananya 33",
        "rating": 5,
        "Comment": "Dosa was Fresh and flavorful."
      },
      {
        "name": "Riya 34",
        "rating": 3,
        "Comment": "Pani Puri was Portion size was acceptable."
      },
      {
        "name": "Nitin 35",
        "rating": 1,
        "Comment": "Dosa was Food arrived cold."
      },
      {
        "name": "Nitin 36",
        "rating": 5,
        "Comment": "Chicken 65 was Loved the quality and presentation."
      },
      {
        "name": "Priya 37",
        "rating": 5,
        "Comment": "Pani Puri was Loved the quality and presentation."
      },
      {
        "name": "Meera 38",
        "rating": 4,
        "Comment": "Tandoori Chicken was Amazing taste, highly recommended."
      },
      {
        "name": "Sanjay 39",
        "rating": 2,
        "Comment": "Mutton Biryani was Food arrived cold."
      },
      {
        "name": "Sneha 40",
        "rating": 5,
        "Comment": "Pani Puri was One of the best dishes I have tried."
      },
      {
        "name": "Sneha 41",
        "rating": 4,
        "Comment": "Mutton Biryani was Loved the quality and presentation."
      },
      {
        "name": "Ananya 42",
        "rating": 4,
        "Comment": "Raj Kachori was Perfectly cooked and worth the price."
      },
      {
        "name": "Sneha 43",
        "rating": 5,
        "Comment": "Veg Fried Rice was Fresh and flavorful."
      },
      {
        "name": "Ananya 44",
        "rating": 4,
        "Comment": "Raj Kachori was One of the best dishes I have tried."
      },
      {
        "name": "Ananya 45",
        "rating": 4,
        "Comment": "Fried Chicken was Loved the quality and presentation."
      },
      {
        "name": "Divya 46",
        "rating": 2,
        "Comment": "Raj Kachori was Not satisfied with the taste."
      },
      {
        "name": "Vikram 47",
        "rating": 5,
        "Comment": "Dosa was Perfectly cooked and worth the price."
      },
      {
        "name": "Ananya 48",
        "rating": 5,
        "Comment": "Momos was Loved the quality and presentation."
      },
      {
        "name": "Neha 49",
        "rating": 4,
        "Comment": "Chole Bhature was Perfectly cooked and worth the price."
      },
      {
        "name": "Divya 50",
        "rating": 4,
        "Comment": "Veg Fried Rice was Fresh and flavorful."
      },
      {
        "name": "Karan 51",
        "rating": 5,
        "Comment": "Veg Fried Rice was Loved the quality and presentation."
      },
      {
        "name": "Aditya 52",
        "rating": 3,
        "Comment": "Pani Puri was Average experience overall."
      },
      {
        "name": "Ishita 53",
        "rating": 5,
        "Comment": "Raj Kachori was Loved the quality and presentation."
      },
      {
        "name": "Ishita 54",
        "rating": 4,
        "Comment": "Paneer Butter Masala was Fresh and flavorful."
      },
      {
        "name": "Nitin 55",
        "rating": 4,
        "Comment": "Tandoori Chicken was Perfectly cooked and worth the price."
      },
      {
        "name": "Pooja 56",
        "rating": 4,
        "Comment": "Chole Bhature was One of the best dishes I have tried."
      },
      {
        "name": "Ananya 57",
        "rating": 3,
        "Comment": "Tandoori Chicken was Food was decent but could be better."
      },
      {
        "name": "Aditya 58",
        "rating": 3,
        "Comment": "Paneer Butter Masala was Average experience overall."
      },
      {
        "name": "Pooja 59",
        "rating": 2,
        "Comment": "Butter Naan was Overpriced for the quality offered."
      },
      {
        "name": "Ananya 60",
        "rating": 5,
        "Comment": "Veg Fried Rice was Loved the quality and presentation."
      },
      {
        "name": "Sanjay 61",
        "rating": 2,
        "Comment": "Chicken 65 was Too much waiting time."
      },
      {
        "name": "Sneha 62",
        "rating": 5,
        "Comment": "Chicken 65 was Amazing taste, highly recommended."
      },
      {
        "name": "Pooja 63",
        "rating": 4,
        "Comment": "Masala Dosa was Fresh and flavorful."
      },
      {
        "name": "Riya 64",
        "rating": 3,
        "Comment": "Dosa was Food was decent but could be better."
      },
      {
        "name": "Aarav 65",
        "rating": 1,
        "Comment": "Sushi was Food arrived cold."
      },
      {
        "name": "Aarav 66",
        "rating": 5,
        "Comment": "Fried Chicken was One of the best dishes I have tried."
      },
      {
        "name": "Nitin 67",
        "rating": 4,
        "Comment": "Pani Puri was Perfectly cooked and worth the price."
      },
      {
        "name": "Kavya 68",
        "rating": 2,
        "Comment": "Dosa was Not satisfied with the taste."
      },
      {
        "name": "Rahul 69",
        "rating": 4,
        "Comment": "Chicken Biryani was Amazing taste, highly recommended."
      },
      {
        "name": "Priya 70",
        "rating": 3,
        "Comment": "Raj Kachori was Food was decent but could be better."
      }
    ],
    "images": [
      {
        "public_id": "empire_restaurant_image_1",
        "url": "https://cf.bstatic.com/xdata/images/hotel/max1024x768/113112095.jpg?k=1c3124fc8057370e97519147fbfd26447c4d1fc38a3ccb47e9d8c972ff2e317a&o=&hp=1"
      }
    ],
    "createdAt": "2024-06-18T00:00:00Z"
  },
  {
    "_id": {
      "$oid": "667176756b69467538f24983"
    },
    "name": "Imperial Restaurant Since 1954",
    "isVeg": false,
    "address": "42/5, Bowring Hospital Rd, Central Street",
    "ratings": 3.7,
    "numOfReviews": 70,
    "location": {
      "type": "Point",
      "coordinates": [
        12.982128633078123,
        77.60318902450435
      ]
    },
    "reviews": [
      {
        "name": "Aditya 1",
        "rating": 4,
        "Comment": "Mutton Biryani was One of the best dishes I have tried."
      },
      {
        "name": "Sneha 2",
        "rating": 4,
        "Comment": "Raj Kachori was Loved the quality and presentation."
      },
      {
        "name": "Pooja 3",
        "rating": 4,
        "Comment": "Veg Fried Rice was Loved the quality and presentation."
      },
      {
        "name": "Meera 4",
        "rating": 5,
        "Comment": "Chicken Biryani was Fresh and flavorful."
      },
      {
        "name": "Riya 5",
        "rating": 5,
        "Comment": "Raj Kachori was Fresh and flavorful."
      },
      {
        "name": "Riya 6",
        "rating": 4,
        "Comment": "Raj Kachori was Amazing taste, highly recommended."
      },
      {
        "name": "Aditya 7",
        "rating": 1,
        "Comment": "Dosa was Too much waiting time."
      },
      {
        "name": "Rohit 8",
        "rating": 5,
        "Comment": "Mutton Biryani was Fresh and flavorful."
      },
      {
        "name": "Riya 9",
        "rating": 4,
        "Comment": "Dosa was Amazing taste, highly recommended."
      },
      {
        "name": "Ananya 10",
        "rating": 5,
        "Comment": "Chicken 65 was One of the best dishes I have tried."
      },
      {
        "name": "Aarav 11",
        "rating": 2,
        "Comment": "Raj Kachori was Not satisfied with the taste."
      },
      {
        "name": "Sanjay 12",
        "rating": 3,
        "Comment": "Paneer Butter Masala was Taste was okay, nothing extraordinary."
      },
      {
        "name": "Kavya 13",
        "rating": 5,
        "Comment": "Chicken Biryani was One of the best dishes I have tried."
      },
      {
        "name": "Vikram 14",
        "rating": 2,
        "Comment": "Chicken Biryani was Too much waiting time."
      },
      {
        "name": "Rohit 15",
        "rating": 5,
        "Comment": "Chicken 65 was Loved the quality and presentation."
      },
      {
        "name": "Rohit 16",
        "rating": 5,
        "Comment": "Sushi was Loved the quality and presentation."
      },
      {
        "name": "Ishita 17",
        "rating": 2,
        "Comment": "Veg Fried Rice was Not satisfied with the taste."
      },
      {
        "name": "Manoj 18",
        "rating": 5,
        "Comment": "Paneer Butter Masala was One of the best dishes I have tried."
      },
      {
        "name": "Aditya 19",
        "rating": 5,
        "Comment": "Paneer Butter Masala was Perfectly cooked and worth the price."
      },
      {
        "name": "Ananya 20",
        "rating": 3,
        "Comment": "Chicken Biryani was Service and food were average."
      },
      {
        "name": "Neha 21",
        "rating": 3,
        "Comment": "Veg Fried Rice was Average experience overall."
      },
      {
        "name": "Aarav 22",
        "rating": 3,
        "Comment": "Sushi was Average experience overall."
      },
      {
        "name": "Karan 23",
        "rating": 5,
        "Comment": "Paneer Butter Masala was Amazing taste, highly recommended."
      },
      {
        "name": "Meera 24",
        "rating": 1,
        "Comment": "Pani Puri was Not satisfied with the taste."
      },
      {
        "name": "Rohit 25",
        "rating": 5,
        "Comment": "Fried Chicken was Perfectly cooked and worth the price."
      },
      {
        "name": "Rahul 26",
        "rating": 3,
        "Comment": "Mutton Biryani was Taste was okay, nothing extraordinary."
      },
      {
        "name": "Kavya 27",
        "rating": 4,
        "Comment": "Chole Bhature was Loved the quality and presentation."
      },
      {
        "name": "Vikram 28",
        "rating": 4,
        "Comment": "Chicken 65 was Amazing taste, highly recommended."
      },
      {
        "name": "Ananya 29",
        "rating": 5,
        "Comment": "Pani Puri was One of the best dishes I have tried."
      },
      {
        "name": "Divya 30",
        "rating": 4,
        "Comment": "Fried Chicken was Loved the quality and presentation."
      },
      {
        "name": "Riya 31",
        "rating": 2,
        "Comment": "Chole Bhature was Overpriced for the quality offered."
      },
      {
        "name": "Sanjay 32",
        "rating": 2,
        "Comment": "Momos was Service needs major improvement."
      },
      {
        "name": "Riya 33",
        "rating": 3,
        "Comment": "Raj Kachori was Food was decent but could be better."
      },
      {
        "name": "Manoj 34",
        "rating": 2,
        "Comment": "Butter Naan was Service needs major improvement."
      },
      {
        "name": "Riya 35",
        "rating": 3,
        "Comment": "Butter Naan was Taste was okay, nothing extraordinary."
      },
      {
        "name": "Vikram 36",
        "rating": 4,
        "Comment": "Chole Bhature was One of the best dishes I have tried."
      },
      {
        "name": "Karan 37",
        "rating": 1,
        "Comment": "Pani Puri was Not satisfied with the taste."
      },
      {
        "name": "Manoj 38",
        "rating": 5,
        "Comment": "Chole Bhature was One of the best dishes I have tried."
      },
      {
        "name": "Sneha 39",
        "rating": 3,
        "Comment": "Masala Dosa was Service and food were average."
      },
      {
        "name": "Divya 40",
        "rating": 5,
        "Comment": "Masala Dosa was Loved the quality and presentation."
      },
      {
        "name": "Aarav 41",
        "rating": 5,
        "Comment": "Fried Chicken was Loved the quality and presentation."
      },
      {
        "name": "Pooja 42",
        "rating": 5,
        "Comment": "Paneer Butter Masala was Amazing taste, highly recommended."
      },
      {
        "name": "Arjun 43",
        "rating": 5,
        "Comment": "Butter Naan was Fresh and flavorful."
      },
      {
        "name": "Rahul 44",
        "rating": 3,
        "Comment": "Chicken Biryani was Average experience overall."
      },
      {
        "name": "Neha 45",
        "rating": 3,
        "Comment": "Butter Naan was Portion size was acceptable."
      },
      {
        "name": "Sanjay 46",
        "rating": 2,
        "Comment": "Sushi was Service needs major improvement."
      },
      {
        "name": "Pooja 47",
        "rating": 5,
        "Comment": "Chole Bhature was Fresh and flavorful."
      },
      {
        "name": "Arjun 48",
        "rating": 3,
        "Comment": "Paneer Butter Masala was Average experience overall."
      },
      {
        "name": "Neha 49",
        "rating": 3,
        "Comment": "Fried Chicken was Food was decent but could be better."
      },
      {
        "name": "Arjun 50",
        "rating": 2,
        "Comment": "Chicken 65 was Overpriced for the quality offered."
      },
      {
        "name": "Karan 51",
        "rating": 2,
        "Comment": "Tandoori Chicken was Service needs major improvement."
      },
      {
        "name": "Rahul 52",
        "rating": 5,
        "Comment": "Tandoori Chicken was Perfectly cooked and worth the price."
      },
      {
        "name": "Divya 53",
        "rating": 2,
        "Comment": "Masala Dosa was Overpriced for the quality offered."
      },
      {
        "name": "Divya 54",
        "rating": 5,
        "Comment": "Chole Bhature was One of the best dishes I have tried."
      },
      {
        "name": "Rohit 55",
        "rating": 3,
        "Comment": "Dosa was Food was decent but could be better."
      },
      {
        "name": "Arjun 56",
        "rating": 4,
        "Comment": "Raj Kachori was Perfectly cooked and worth the price."
      },
      {
        "name": "Aditya 57",
        "rating": 1,
        "Comment": "Veg Fried Rice was Food arrived cold."
      },
      {
        "name": "Pooja 58",
        "rating": 5,
        "Comment": "Chicken Biryani was One of the best dishes I have tried."
      },
      {
        "name": "Kavya 59",
        "rating": 5,
        "Comment": "Chicken 65 was One of the best dishes I have tried."
      },
      {
        "name": "Manoj 60",
        "rating": 5,
        "Comment": "Sushi was Amazing taste, highly recommended."
      },
      {
        "name": "Karan 61",
        "rating": 5,
        "Comment": "Chole Bhature was Amazing taste, highly recommended."
      },
      {
        "name": "Rohit 62",
        "rating": 5,
        "Comment": "Fried Chicken was Perfectly cooked and worth the price."
      },
      {
        "name": "Vikram 63",
        "rating": 3,
        "Comment": "Masala Dosa was Food was decent but could be better."
      },
      {
        "name": "Ananya 64",
        "rating": 5,
        "Comment": "Chole Bhature was Amazing taste, highly recommended."
      },
      {
        "name": "Sneha 65",
        "rating": 4,
        "Comment": "Fried Chicken was Perfectly cooked and worth the price."
      },
      {
        "name": "Neha 66",
        "rating": 3,
        "Comment": "Masala Dosa was Taste was okay, nothing extraordinary."
      },
      {
        "name": "Priya 67",
        "rating": 2,
        "Comment": "Mutton Biryani was Too much waiting time."
      },
      {
        "name": "Pooja 68",
        "rating": 5,
        "Comment": "Butter Naan was One of the best dishes I have tried."
      },
      {
        "name": "Neha 69",
        "rating": 5,
        "Comment": "Sushi was One of the best dishes I have tried."
      },
      {
        "name": "Vikram 70",
        "rating": 4,
        "Comment": "Chicken Biryani was One of the best dishes I have tried."
      }
    ],
    "images": [
      {
        "public_id": "image1",
        "url": "https://shorturl.at/Sdwal"
      }
    ]
  },
  {
    "_id": {
      "$oid": "66717b16e1a78e67dc8c8df1"
    },
    "name": "Meghana's Biryani",
    "isVeg": false,
    "address": "1st Floor, 57 Residency Road, Near Old Galaxy Theater, Bengaluru 560025, India",
    "ratings": 3.5,
    "numOfReviews": 70,
    "location": {
      "type": "Point",
      "coordinates": [
        77.6066,
        12.9738
      ]
    },
    "reviews": [
      {
        "name": "Arjun 1",
        "rating": 2,
        "Comment": "Momos was Service needs major improvement."
      },
      {
        "name": "Aditya 2",
        "rating": 4,
        "Comment": "Chicken 65 was Perfectly cooked and worth the price."
      },
      {
        "name": "Rahul 3",
        "rating": 4,
        "Comment": "Dosa was Perfectly cooked and worth the price."
      },
      {
        "name": "Vikram 4",
        "rating": 4,
        "Comment": "Veg Fried Rice was Fresh and flavorful."
      },
      {
        "name": "Meera 5",
        "rating": 4,
        "Comment": "Raj Kachori was Fresh and flavorful."
      },
      {
        "name": "Karan 6",
        "rating": 4,
        "Comment": "Butter Naan was Loved the quality and presentation."
      },
      {
        "name": "Ananya 7",
        "rating": 2,
        "Comment": "Masala Dosa was Too much waiting time."
      },
      {
        "name": "Aditya 8",
        "rating": 3,
        "Comment": "Chicken Biryani was Average experience overall."
      },
      {
        "name": "Nitin 9",
        "rating": 3,
        "Comment": "Chole Bhature was Food was decent but could be better."
      },
      {
        "name": "Rohit 10",
        "rating": 5,
        "Comment": "Chole Bhature was Perfectly cooked and worth the price."
      },
      {
        "name": "Ananya 11",
        "rating": 5,
        "Comment": "Paneer Butter Masala was Perfectly cooked and worth the price."
      },
      {
        "name": "Rohit 12",
        "rating": 5,
        "Comment": "Mutton Biryani was Fresh and flavorful."
      },
      {
        "name": "Divya 13",
        "rating": 3,
        "Comment": "Pani Puri was Taste was okay, nothing extraordinary."
      },
      {
        "name": "Ananya 14",
        "rating": 4,
        "Comment": "Raj Kachori was Fresh and flavorful."
      },
      {
        "name": "Karan 15",
        "rating": 5,
        "Comment": "Butter Naan was Fresh and flavorful."
      },
      {
        "name": "Priya 16",
        "rating": 2,
        "Comment": "Paneer Butter Masala was Overpriced for the quality offered."
      },
      {
        "name": "Neha 17",
        "rating": 4,
        "Comment": "Butter Naan was Loved the quality and presentation."
      },
      {
        "name": "Karan 18",
        "rating": 3,
        "Comment": "Paneer Butter Masala was Portion size was acceptable."
      },
      {
        "name": "Riya 19",
        "rating": 4,
        "Comment": "Pani Puri was Amazing taste, highly recommended."
      },
      {
        "name": "Vikram 20",
        "rating": 3,
        "Comment": "Raj Kachori was Food was decent but could be better."
      },
      {
        "name": "Nitin 21",
        "rating": 4,
        "Comment": "Butter Naan was Perfectly cooked and worth the price."
      },
      {
        "name": "Ananya 22",
        "rating": 5,
        "Comment": "Paneer Butter Masala was Perfectly cooked and worth the price."
      },
      {
        "name": "Neha 23",
        "rating": 5,
        "Comment": "Paneer Butter Masala was One of the best dishes I have tried."
      },
      {
        "name": "Riya 24",
        "rating": 1,
        "Comment": "Pani Puri was Service needs major improvement."
      },
      {
        "name": "Ananya 25",
        "rating": 5,
        "Comment": "Butter Naan was Loved the quality and presentation."
      },
      {
        "name": "Sanjay 26",
        "rating": 5,
        "Comment": "Fried Chicken was One of the best dishes I have tried."
      },
      {
        "name": "Riya 27",
        "rating": 3,
        "Comment": "Masala Dosa was Average experience overall."
      },
      {
        "name": "Ishita 28",
        "rating": 4,
        "Comment": "Raj Kachori was Amazing taste, highly recommended."
      },
      {
        "name": "Sneha 29",
        "rating": 3,
        "Comment": "Tandoori Chicken was Portion size was acceptable."
      },
      {
        "name": "Aarav 30",
        "rating": 5,
        "Comment": "Raj Kachori was Fresh and flavorful."
      },
      {
        "name": "Arjun 31",
        "rating": 5,
        "Comment": "Mutton Biryani was Perfectly cooked and worth the price."
      },
      {
        "name": "Rohit 32",
        "rating": 4,
        "Comment": "Chicken Biryani was Fresh and flavorful."
      },
      {
        "name": "Rohit 33",
        "rating": 5,
        "Comment": "Raj Kachori was Loved the quality and presentation."
      },
      {
        "name": "Vikram 34",
        "rating": 4,
        "Comment": "Chole Bhature was Fresh and flavorful."
      },
      {
        "name": "Nitin 35",
        "rating": 4,
        "Comment": "Sushi was Loved the quality and presentation."
      },
      {
        "name": "Sneha 36",
        "rating": 3,
        "Comment": "Fried Chicken was Service and food were average."
      },
      {
        "name": "Karan 37",
        "rating": 4,
        "Comment": "Tandoori Chicken was One of the best dishes I have tried."
      },
      {
        "name": "Ananya 38",
        "rating": 4,
        "Comment": "Veg Fried Rice was Perfectly cooked and worth the price."
      },
      {
        "name": "Kavya 39",
        "rating": 4,
        "Comment": "Veg Fried Rice was One of the best dishes I have tried."
      },
      {
        "name": "Pooja 40",
        "rating": 5,
        "Comment": "Momos was Perfectly cooked and worth the price."
      },
      {
        "name": "Priya 41",
        "rating": 1,
        "Comment": "Butter Naan was Service needs major improvement."
      },
      {
        "name": "Pooja 42",
        "rating": 4,
        "Comment": "Chole Bhature was Loved the quality and presentation."
      },
      {
        "name": "Rahul 43",
        "rating": 5,
        "Comment": "Chicken Biryani was One of the best dishes I have tried."
      },
      {
        "name": "Divya 44",
        "rating": 2,
        "Comment": "Sushi was Food arrived cold."
      },
      {
        "name": "Neha 45",
        "rating": 4,
        "Comment": "Momos was Fresh and flavorful."
      },
      {
        "name": "Ishita 46",
        "rating": 1,
        "Comment": "Sushi was Not satisfied with the taste."
      },
      {
        "name": "Rohit 47",
        "rating": 2,
        "Comment": "Chole Bhature was Too much waiting time."
      },
      {
        "name": "Kavya 48",
        "rating": 5,
        "Comment": "Fried Chicken was Amazing taste, highly recommended."
      },
      {
        "name": "Kavya 49",
        "rating": 4,
        "Comment": "Chicken 65 was One of the best dishes I have tried."
      },
      {
        "name": "Ananya 50",
        "rating": 4,
        "Comment": "Tandoori Chicken was Loved the quality and presentation."
      },
      {
        "name": "Sanjay 51",
        "rating": 2,
        "Comment": "Chicken Biryani was Not satisfied with the taste."
      },
      {
        "name": "Priya 52",
        "rating": 5,
        "Comment": "Raj Kachori was Amazing taste, highly recommended."
      },
      {
        "name": "Pooja 53",
        "rating": 2,
        "Comment": "Chole Bhature was Food arrived cold."
      },
      {
        "name": "Riya 54",
        "rating": 2,
        "Comment": "Mutton Biryani was Food arrived cold."
      },
      {
        "name": "Aarav 55",
        "rating": 4,
        "Comment": "Tandoori Chicken was Loved the quality and presentation."
      },
      {
        "name": "Riya 56",
        "rating": 5,
        "Comment": "Fried Chicken was Perfectly cooked and worth the price."
      },
      {
        "name": "Sneha 57",
        "rating": 1,
        "Comment": "Mutton Biryani was Food arrived cold."
      },
      {
        "name": "Kavya 58",
        "rating": 3,
        "Comment": "Pani Puri was Average experience overall."
      },
      {
        "name": "Arjun 59",
        "rating": 2,
        "Comment": "Mutton Biryani was Not satisfied with the taste."
      },
      {
        "name": "Manoj 60",
        "rating": 5,
        "Comment": "Masala Dosa was One of the best dishes I have tried."
      },
      {
        "name": "Priya 61",
        "rating": 2,
        "Comment": "Mutton Biryani was Too much waiting time."
      },
      {
        "name": "Nitin 62",
        "rating": 1,
        "Comment": "Raj Kachori was Not satisfied with the taste."
      },
      {
        "name": "Meera 63",
        "rating": 3,
        "Comment": "Chole Bhature was Portion size was acceptable."
      },
      {
        "name": "Aarav 64",
        "rating": 4,
        "Comment": "Dosa was One of the best dishes I have tried."
      },
      {
        "name": "Aditya 65",
        "rating": 4,
        "Comment": "Masala Dosa was Amazing taste, highly recommended."
      },
      {
        "name": "Vikram 66",
        "rating": 4,
        "Comment": "Chicken 65 was Amazing taste, highly recommended."
      },
      {
        "name": "Vikram 67",
        "rating": 1,
        "Comment": "Paneer Butter Masala was Overpriced for the quality offered."
      },
      {
        "name": "Manoj 68",
        "rating": 5,
        "Comment": "Pani Puri was Perfectly cooked and worth the price."
      },
      {
        "name": "Nitin 69",
        "rating": 1,
        "Comment": "Tandoori Chicken was Overpriced for the quality offered."
      },
      {
        "name": "Sneha 70",
        "rating": 4,
        "Comment": "Chicken Biryani was Amazing taste, highly recommended."
      }
    ],
    "images": [
      {
        "public_id": "image1",
        "url": "https://tse4.mm.bing.net/th?id=OIG2.HoKkNfx8R_.WKzdDzd2z&pid=ImgGn"
      }
    ]
  },
  {
    "_id": {
      "$oid": "667158dec45b2f6c5ad027d3"
    },
    "name": "Daily Sushi",
    "isVeg": false,
    "address": "3rd Sector, HSR Layout, Banglore",
    "ratings": 3.2,
    "numOfReviews": 70,
    "location": {
      "type": "Point",
      "coordinates": [
        -122.4194,
        37.7749
      ]
    },
    "reviews": [
      {
        "name": "Arjun 1",
        "rating": 4,
        "Comment": "Chole Bhature was Amazing taste, highly recommended."
      },
      {
        "name": "Vikram 2",
        "rating": 1,
        "Comment": "Paneer Butter Masala was Not satisfied with the taste."
      },
      {
        "name": "Ananya 3",
        "rating": 2,
        "Comment": "Raj Kachori was Overpriced for the quality offered."
      },
      {
        "name": "Nitin 4",
        "rating": 5,
        "Comment": "Momos was Perfectly cooked and worth the price."
      },
      {
        "name": "Manoj 5",
        "rating": 4,
        "Comment": "Pani Puri was Amazing taste, highly recommended."
      },
      {
        "name": "Arjun 6",
        "rating": 3,
        "Comment": "Chole Bhature was Food was decent but could be better."
      },
      {
        "name": "Meera 7",
        "rating": 1,
        "Comment": "Momos was Not satisfied with the taste."
      },
      {
        "name": "Ananya 8",
        "rating": 1,
        "Comment": "Mutton Biryani was Overpriced for the quality offered."
      },
      {
        "name": "Vikram 9",
        "rating": 2,
        "Comment": "Raj Kachori was Food arrived cold."
      },
      {
        "name": "Pooja 10",
        "rating": 3,
        "Comment": "Pani Puri was Service and food were average."
      },
      {
        "name": "Divya 11",
        "rating": 3,
        "Comment": "Veg Fried Rice was Portion size was acceptable."
      },
      {
        "name": "Vikram 12",
        "rating": 4,
        "Comment": "Momos was Fresh and flavorful."
      },
      {
        "name": "Pooja 13",
        "rating": 3,
        "Comment": "Sushi was Food was decent but could be better."
      },
      {
        "name": "Priya 14",
        "rating": 1,
        "Comment": "Tandoori Chicken was Overpriced for the quality offered."
      },
      {
        "name": "Rohit 15",
        "rating": 4,
        "Comment": "Mutton Biryani was Amazing taste, highly recommended."
      },
      {
        "name": "Manoj 16",
        "rating": 2,
        "Comment": "Chole Bhature was Not satisfied with the taste."
      },
      {
        "name": "Priya 17",
        "rating": 4,
        "Comment": "Raj Kachori was Loved the quality and presentation."
      },
      {
        "name": "Priya 18",
        "rating": 3,
        "Comment": "Raj Kachori was Service and food were average."
      },
      {
        "name": "Arjun 19",
        "rating": 1,
        "Comment": "Chicken 65 was Service needs major improvement."
      },
      {
        "name": "Karan 20",
        "rating": 5,
        "Comment": "Veg Fried Rice was Loved the quality and presentation."
      },
      {
        "name": "Pooja 21",
        "rating": 2,
        "Comment": "Butter Naan was Too much waiting time."
      },
      {
        "name": "Aarav 22",
        "rating": 4,
        "Comment": "Masala Dosa was One of the best dishes I have tried."
      },
      {
        "name": "Aarav 23",
        "rating": 4,
        "Comment": "Masala Dosa was One of the best dishes I have tried."
      },
      {
        "name": "Arjun 24",
        "rating": 2,
        "Comment": "Chicken 65 was Service needs major improvement."
      },
      {
        "name": "Priya 25",
        "rating": 4,
        "Comment": "Chicken 65 was One of the best dishes I have tried."
      },
      {
        "name": "Aarav 26",
        "rating": 5,
        "Comment": "Sushi was One of the best dishes I have tried."
      },
      {
        "name": "Divya 27",
        "rating": 2,
        "Comment": "Momos was Overpriced for the quality offered."
      },
      {
        "name": "Nitin 28",
        "rating": 3,
        "Comment": "Raj Kachori was Average experience overall."
      },
      {
        "name": "Vikram 29",
        "rating": 2,
        "Comment": "Chicken 65 was Too much waiting time."
      },
      {
        "name": "Rohit 30",
        "rating": 2,
        "Comment": "Fried Chicken was Food arrived cold."
      },
      {
        "name": "Priya 31",
        "rating": 1,
        "Comment": "Chole Bhature was Not satisfied with the taste."
      },
      {
        "name": "Ananya 32",
        "rating": 3,
        "Comment": "Veg Fried Rice was Portion size was acceptable."
      },
      {
        "name": "Ananya 33",
        "rating": 5,
        "Comment": "Chole Bhature was Loved the quality and presentation."
      },
      {
        "name": "Rahul 34",
        "rating": 5,
        "Comment": "Dosa was One of the best dishes I have tried."
      },
      {
        "name": "Pooja 35",
        "rating": 4,
        "Comment": "Chicken 65 was Amazing taste, highly recommended."
      },
      {
        "name": "Karan 36",
        "rating": 3,
        "Comment": "Dosa was Average experience overall."
      },
      {
        "name": "Meera 37",
        "rating": 1,
        "Comment": "Butter Naan was Not satisfied with the taste."
      },
      {
        "name": "Sneha 38",
        "rating": 5,
        "Comment": "Chole Bhature was Amazing taste, highly recommended."
      },
      {
        "name": "Vikram 39",
        "rating": 4,
        "Comment": "Paneer Butter Masala was Amazing taste, highly recommended."
      },
      {
        "name": "Rahul 40",
        "rating": 4,
        "Comment": "Chole Bhature was Loved the quality and presentation."
      },
      {
        "name": "Neha 41",
        "rating": 5,
        "Comment": "Momos was Perfectly cooked and worth the price."
      },
      {
        "name": "Pooja 42",
        "rating": 4,
        "Comment": "Chicken Biryani was Perfectly cooked and worth the price."
      },
      {
        "name": "Ishita 43",
        "rating": 1,
        "Comment": "Paneer Butter Masala was Too much waiting time."
      },
      {
        "name": "Rohit 44",
        "rating": 2,
        "Comment": "Chicken Biryani was Not satisfied with the taste."
      },
      {
        "name": "Nitin 45",
        "rating": 2,
        "Comment": "Veg Fried Rice was Service needs major improvement."
      },
      {
        "name": "Sanjay 46",
        "rating": 3,
        "Comment": "Masala Dosa was Taste was okay, nothing extraordinary."
      },
      {
        "name": "Ananya 47",
        "rating": 3,
        "Comment": "Chole Bhature was Food was decent but could be better."
      },
      {
        "name": "Kavya 48",
        "rating": 4,
        "Comment": "Chicken Biryani was Perfectly cooked and worth the price."
      },
      {
        "name": "Sneha 49",
        "rating": 5,
        "Comment": "Fried Chicken was Perfectly cooked and worth the price."
      },
      {
        "name": "Nitin 50",
        "rating": 4,
        "Comment": "Fried Chicken was Loved the quality and presentation."
      },
      {
        "name": "Ananya 51",
        "rating": 4,
        "Comment": "Butter Naan was Loved the quality and presentation."
      },
      {
        "name": "Rahul 52",
        "rating": 5,
        "Comment": "Dosa was Amazing taste, highly recommended."
      },
      {
        "name": "Sneha 53",
        "rating": 5,
        "Comment": "Masala Dosa was Fresh and flavorful."
      },
      {
        "name": "Rohit 54",
        "rating": 2,
        "Comment": "Momos was Food arrived cold."
      },
      {
        "name": "Sneha 55",
        "rating": 5,
        "Comment": "Mutton Biryani was Loved the quality and presentation."
      },
      {
        "name": "Rohit 56",
        "rating": 5,
        "Comment": "Chicken Biryani was Loved the quality and presentation."
      },
      {
        "name": "Priya 57",
        "rating": 2,
        "Comment": "Momos was Service needs major improvement."
      },
      {
        "name": "Rohit 58",
        "rating": 4,
        "Comment": "Paneer Butter Masala was Loved the quality and presentation."
      },
      {
        "name": "Arjun 59",
        "rating": 2,
        "Comment": "Paneer Butter Masala was Food arrived cold."
      },
      {
        "name": "Karan 60",
        "rating": 5,
        "Comment": "Pani Puri was Amazing taste, highly recommended."
      },
      {
        "name": "Priya 61",
        "rating": 1,
        "Comment": "Masala Dosa was Overpriced for the quality offered."
      },
      {
        "name": "Divya 62",
        "rating": 3,
        "Comment": "Fried Chicken was Food was decent but could be better."
      },
      {
        "name": "Manoj 63",
        "rating": 1,
        "Comment": "Tandoori Chicken was Food arrived cold."
      },
      {
        "name": "Vikram 64",
        "rating": 2,
        "Comment": "Fried Chicken was Overpriced for the quality offered."
      },
      {
        "name": "Nitin 65",
        "rating": 1,
        "Comment": "Pani Puri was Too much waiting time."
      },
      {
        "name": "Arjun 66",
        "rating": 2,
        "Comment": "Masala Dosa was Service needs major improvement."
      },
      {
        "name": "Arjun 67",
        "rating": 5,
        "Comment": "Chole Bhature was One of the best dishes I have tried."
      },
      {
        "name": "Priya 68",
        "rating": 5,
        "Comment": "Chicken 65 was Amazing taste, highly recommended."
      },
      {
        "name": "Rohit 69",
        "rating": 4,
        "Comment": "Fried Chicken was One of the best dishes I have tried."
      },
      {
        "name": "Meera 70",
        "rating": 5,
        "Comment": "Fried Chicken was One of the best dishes I have tried."
      }
    ],
    "images": [
      {
        "public_id": "daily_sushi_img_01",
        "url": "https://b.zmtcdn.com/data/pictures/6/20583196/d538d11cd05d443edac17955bb3fdaae.jpg?output-format=webp&fit=around|771.75:416.25&crop=771.75:416.25;*,*"
      },
      {
        "public_id": "daily_sushi_img_02",
        "url": "https://tb-static.uber.com/prod/image-proc/processed_images/f836ab1bbffb846981d3aa8776d0361e/fb86662148be855d931b37d6c1e5fcbe.jpeg"
      }
    ]
  }
]